solai_db/__init__.py
solai_db/database.py
solai_db/models/__init__.py
solai_db/models/base.py
solai_db/models/company.py
solai_db/models/public.py
solai_db/models/token_vault.py
solai_db-0.1.15.dist-info/METADATA
solai_db-0.1.15.dist-info/WHEEL
solai_db-0.1.15.dist-info/top_level.txt
solai_db-0.1.15.dist-info/RECORD
