Metadata-Version: 2.2
Name: solai-db
Version: 0.1.15
Summary: The database for SolAI
Author: SolAI
Requires-Dist: sqlalchemy>=2.0.0
Requires-Dist: psycopg2-binary>=2.9.0
Dynamic: author
Dynamic: requires-dist
Dynamic: summary
